orangecontrib/__init__.py
orangecontrib/orange3example/__init__.py
orangecontrib/orange3example/utils/llm.py
orangecontrib/orange3example/utils/microbit.py
orangecontrib/orange3example/utils/webcam.py
orangecontrib/orange3example/widgets/__init__.py
orangecontrib/orange3example/widgets/owimagellm.py
orangecontrib/orange3example/widgets/owllmtransformer.py
orangecontrib/orange3example/widgets/owmicrobit.py
orangecontrib/orange3example/widgets/owwebcam.py
orange3_example-0.1.15.dist-info/METADATA
orange3_example-0.1.15.dist-info/WHEEL
orange3_example-0.1.15.dist-info/entry_points.txt
orange3_example-0.1.15.dist-info/top_level.txt
orange3_example-0.1.15.dist-info/RECORD
