Metadata-Version: 2.1
Name: orange3-example
Version: 0.1.15
Summary: Orange3 LLM 기반 사용자 정의 예제 위젯입니다.
Home-page: https://github.com/whyz-dev/orange3-widget
Author: Gangjun Jo
License: MIT
Classifier: Programming Language :: Python :: 3
Classifier: License :: OSI Approved :: MIT License
Requires-Dist: Orange3>=3.32.0
Requires-Dist: openai
Requires-Dist: python-dotenv
Requires-Dist: pyserial
Requires-Dist: opencv-python-headless==4.9.0.80
